viswanth/__init__.py
viswanth/ai_lab.py
viswanth-1.0.0.dist-info/METADATA
viswanth-1.0.0.dist-info/WHEEL
viswanth-1.0.0.dist-info/top_level.txt
viswanth-1.0.0.dist-info/RECORD
