Metadata-Version: 2.4
Name: viswanth
Version: 1.0.0
Summary: Offline Conversational AI Lab Experiments (7–10)
Author: Viswanth S S
Author-email: viswanth@example.com
Classifier: Programming Language :: Python :: 3
Classifier: Operating System :: OS Independent
Requires-Python: >=3.8
Requires-Dist: flask
Requires-Dist: nltk
Requires-Dist: pyttsx3
Dynamic: author
Dynamic: author-email
Dynamic: classifier
Dynamic: description
Dynamic: description-content-type
Dynamic: requires-dist
Dynamic: requires-python
Dynamic: summary
